nonebot_plugin_maimai_helper/__init__.py
nonebot_plugin_maimai_helper/data.py
nonebot_plugin_maimai_helper/game_data/chara_list.json
nonebot_plugin_maimai_helper/game_data/diving_music_list.json
nonebot_plugin_maimai_helper/game_data/frame_list.json
nonebot_plugin_maimai_helper/game_data/icon_list.json
nonebot_plugin_maimai_helper/game_data/music_alias_list.json
nonebot_plugin_maimai_helper/game_data/music_list.json
nonebot_plugin_maimai_helper/game_data/partner_list.json
nonebot_plugin_maimai_helper/game_data/plate_list.json
nonebot_plugin_maimai_helper/game_data/title_list.json
nonebot_plugin_maimai_helper/helper/__init__.py
nonebot_plugin_maimai_helper/helper/diving_fish.py
nonebot_plugin_maimai_helper/helper/simai.py
nonebot_plugin_maimai_helper/manager/__init__.py
nonebot_plugin_maimai_helper/manager/game_data.py
nonebot_plugin_maimai_helper/manager/usage_count.py
nonebot_plugin_maimai_helper/update_music_list.py
nonebot_plugin_maimai_helper/util/__init__.py
nonebot_plugin_maimai_helper/util/net/__init__.py
nonebot_plugin_maimai_helper/util/net/crypto.py
nonebot_plugin_maimai_helper/util/net/HTTPRequest.py
nonebot_plugin_maimai_helper/util/net/SocketHttps.py
nonebot_plugin_maimai_helper/util/utils.py
nonebot_plugin_maimai_helper-1.3.4.dist-info/LICENSE
nonebot_plugin_maimai_helper-1.3.4.dist-info/METADATA
nonebot_plugin_maimai_helper-1.3.4.dist-info/WHEEL
nonebot_plugin_maimai_helper-1.3.4.dist-info/RECORD
