Metadata-Version: 2.1
Name: nonebot_plugin_maimai_helper
Version: 1.3.4
Summary: Nonebot2 plugin for maimaiDX game account support function
Home-page: https://github.com/YTSakura233/nonebot_plugin_maimai_helper
License: MIT
Author: YTSakura233
Author-email: jionglian5566@gmail.com
Requires-Python: >=3.8,<4.0
Classifier: License :: OSI Approved :: MIT License
Classifier: Programming Language :: Python :: 3
Classifier: Programming Language :: Python :: 3.8
Classifier: Programming Language :: Python :: 3.9
Classifier: Programming Language :: Python :: 3.10
Classifier: Programming Language :: Python :: 3.11
Classifier: Programming Language :: Python :: 3.12
Classifier: Programming Language :: Python :: 3.13
Requires-Dist: cryptography (>=42.0.0)
Requires-Dist: nonebot-adapter-onebot (>=2.1.1,<3.0.0)
Requires-Dist: nonebot2[fastapi] (>=2.0.0-rc.1,<3.0.0)
Requires-Dist: pymysql (>=1.0.0)
Requires-Dist: requests (>=2.20.1)
Requires-Dist: urllib3 (>=2.2.0)
Project-URL: Repository, https://github.com/YTSakura233/nonebot_plugin_maimai_helper
